coreason_veritas/__init__.py
coreason_veritas/anchor.py
coreason_veritas/auditor.py
coreason_veritas/exceptions.py
coreason_veritas/gatekeeper.py
coreason_veritas/logging_utils.py
coreason_veritas/main.py
coreason_veritas/py.typed
coreason_veritas/quota.py
coreason_veritas/resilience.py
coreason_veritas/sanitizer.py
coreason_veritas/server.py
coreason_veritas/wrapper.py
coreason_veritas-0.12.0.dist-info/METADATA
coreason_veritas-0.12.0.dist-info/WHEEL
coreason_veritas-0.12.0.dist-info/licenses/LICENSE
coreason_veritas-0.12.0.dist-info/licenses/NOTICE
coreason_veritas-0.12.0.dist-info/RECORD
