Metadata-Version: 2.4
Name: coreason-veritas
Version: 0.12.0
Summary: coreason_veritas is the non-negotiable governance layer of the CoReason platform (Prosperity Public License 3.0.0)
License: Proprietary
License-File: LICENSE
License-File: NOTICE
Author: Gowtham A Rao
Author-email: gowtham.rao@coreason.ai
Requires-Python: >=3.12,<3.15
Classifier: Development Status :: 4 - Beta
Classifier: Intended Audience :: Developers
Classifier: Intended Audience :: Information Technology
Classifier: License :: Other/Proprietary License
Classifier: Operating System :: OS Independent
Classifier: Programming Language :: Python :: 3
Classifier: Programming Language :: Python :: 3.12
Classifier: Programming Language :: Python :: 3.13
Classifier: Programming Language :: Python :: 3.14
Classifier: Topic :: Security
Classifier: Topic :: Software Development :: Libraries :: Python Modules
Classifier: Topic :: System :: Systems Administration :: Authentication/Directory
Requires-Dist: anyio (>=4.12.1,<5.0.0)
Requires-Dist: coreason-identity (>=0.4.1,<0.5.0)
Requires-Dist: coreason-validator (>=0.5.1,<0.6.0)
Requires-Dist: cryptography (>=46.0.4,<47.0.0)
Requires-Dist: fastapi (==0.128.0)
Requires-Dist: httpx (>=0.28.1,<0.29.0)
Requires-Dist: jcs (>=0.2.1,<0.3.0)
Requires-Dist: loguru (>=0.7.2,<0.8.0)
Requires-Dist: opentelemetry-api (>=1.39.1,<2.0.0)
Requires-Dist: opentelemetry-exporter-otlp (>=1.39.1,<2.0.0)
Requires-Dist: opentelemetry-instrumentation-fastapi (>=0.60b1,<0.61)
Requires-Dist: presidio-analyzer (>=2.2.355,<3.0.0)
Requires-Dist: redis (>=7.1.0,<8.0.0)
Requires-Dist: spacy (>=3.7.2,<4.0.0)
Requires-Dist: urllib3 (>=2.6.3,<3.0.0)
Requires-Dist: uvicorn (==0.40.0)
Project-URL: Documentation, https://github.com/CoReason-AI/coreason_veritas
Project-URL: Homepage, https://github.com/CoReason-AI/coreason_veritas
Project-URL: Repository, https://github.com/CoReason-AI/coreason_veritas
